[
    {
      "elementType": "geometry",
      "stylers": [
        { "color": "#e5e3df" }
      ]
    },
    {
      "elementType": "labels.text.fill",
      "stylers": [
        { "color": "#3c3c3c" }
      ]
    },
    {
      "elementType": "labels.text.stroke",
      "stylers": [
        { "color": "#ffffff" }
      ]
    },
    {
      "featureType": "water",
      "elementType": "geometry",
      "stylers": [
        { "color": "#76bde0" }
      ]
    },
    {
      "featureType": "road",
      "elementType": "geometry",
      "stylers": [
        { "color": "#ffffff" }
      ]
    },
    {
      "featureType": "road",
      "elementType": "labels.text.fill",
      "stylers": [
        { "color": "#999999" }
      ]
    },
    {
      "featureType": "landscape",
      "elementType": "geometry",
      "stylers": [
        { "color": "#d7e4c4" }
      ]
    },
    {
      "featureType": "poi",
      "elementType": "geometry",
      "stylers": [
        { "color": "#e6e6e6" }
      ]
    },
    {
      "featureType": "transit",
      "elementType": "geometry",
      "stylers": [
        { "color": "#d1d1d1" }
      ]
    }
  ]
  